Workbook

Sheet UNILAB - CUSTOS
A1: Descrição | B1: valor
A2: 2,5 HEXANODIONA, URINA ISOLADA | B2: 17.7
A3: 25-HIDROXI VITAMINA D | B3: 19.5
A4: ACETONA | B4: 55
A5: ACETONA - INICIO DE JORNADA DE TRABALHO | B5: 22
A6: ACETONA, URINA ISOLADA | B6: 22
A7: ACIDO 2 TIO TIAZOLIDINA | B7: 280
A8: ÁCIDO BUTOXIACÉTICO | B8: 310
A9: ACIDO DELTA AMINO LEVULINICO, URINA ISOLADA | B9: 14
A10: ACIDO FENILGLIOXILICO | B10: 34
A11: ACIDO FOLICO | B11: 28
A12: ACIDO FOLICO - POS FILTRO | B12: 15
A13: ACIDO FOLICO - POS HEMODIALISE | B13: 28
... A97: COLINESTERASE PLASMATICA | B97: 4.5
A98: COPROCULTURA | B98: a
A99: COPROCULTURA (EMPRESAS) | B99: 13.5
A100: COPROCULTURA, EMPRESAS | B100: 13.5
A101: CORONAVÍRUS 2019 (SARS-CoV-2), ANTÍGENOS | B101: 80
A102: CORONAVÍRUS 2019 (SARS-CoV-2), ANTÍGENOS - BOSCH | B102: 80
A103: CORTISOL | B103: 20
A104: CORTISOL - DILUIÇÃO | B104: 20
A105: CREATINA SERICA | B105: 22
A106: CREATININA SERICA | B106: 2.7
A107: CREATININA SERICA - NEFRO | B107: 2.7
A108: CREATININA, URINA 12 HORAS | B108: 7
A109: CREATININA, URINA 24 HORAS | B109: 7
A110: CREATININA, URINA ISOLADA | B110: 7
... A360: ZINCO PROTOPORFIRINA | B360: 39

Sheet UNILAB - MAIS VENDIDOS
B1: CENTRO MÉDICO INTEGRADO 2026
B2: UNILAB - EXAMES LABORATORIAIS
B3: EXAMES MAIS UTILIZADOS
B4: QTDE | C4: MNEMÔNICO | D4: PROCEDIMENTO | E4: VALOR
B5: 1 | C5: ACFOL | D5: ÁCIDO FÓLICO | E5: ='UNILAB - RELATÓRIO VENDAS'!E6 -> 47.6
B6: 2 | C6: HIPURIS | D6: ÁCIDO HIPÚRICO | E6: ='UNILAB - RELATÓRIO VENDAS'!E8 -> 19
B7: 3 | C7: METHURIS | D7: ÁCIDO METIL HIPÚRICO | E7: ='UNILAB - RELATÓRIO VENDAS'!E10 -> 19
B8: 4 | C8: ACUR | D8: ÁCIDO ÚRICO | E8: ='UNILAB - RELATÓRIO VENDAS'!E11 -> 6
B9: 5 | C9: CA | D9: CÁLCIO | E9: ='UNILAB - RELATÓRIO VENDAS'!E28 -> 7
B10: 6 | C10: COL | D10: COLESTEROL TOTAL | E10: ='UNILAB - RELATÓRIO VENDAS'!E32 -> 24.5
B11: 7 | C11: COLTF | D11: COLESTEROL TOTAL E FRAÇÕES | E11: ='UNILAB - RELATÓRIO VENDAS'!E33 -> 58
B12: 8 | C12: COPRO | D12: COPROCULTURA | E12: ='UNILAB - RELATÓRIO VENDAS'!E34 -> 23
B13: 9 | C13: CPK | D13: CPK | E13: ='UNILAB - RELATÓRIO VENDAS'!E38 -> 12.3
B14: 10 | C14: CRE | D14: CREATININA | E14: ='UNILAB - RELATÓRIO VENDAS'!E37 -> 6
B15: 11 | C15: FAN | D15: FATOR ANTI NUCLEO | E15: ='UNILAB - RELATÓRIO VENDAS'!E53 -> 34
B16: 12 | C16: FREUM | D16: FATOR REUMATOIDE | E16: ='UNILAB - RELATÓRIO VENDAS'!E54 -> 30.6
B17: 13 | C17: FERR | D17: FERRITINA | E17: ='UNILAB - RELATÓRIO VENDAS'!E56 -> 59.5
B18: 14 | C18: FE | D18: FERRO | E18: ='UNILAB - RELATÓRIO VENDAS'!E57 -> 13
B19: 15 | C19: GLI | D19: GLICOSE | E19: ='UNILAB - RELATÓRIO VENDAS'!E66 -> 6
B20: 16 | C20: HDL | D20: HDL | E20: ='UNILAB - RELATÓRIO VENDAS'!E69 -> 24.5
B21: 17 | C21: HBA1C | D21: HEMOGLOBINA GLICADA | E21: 23
B22: 18 | C22: HEMO | D22: HEMOGRAMA COMPLETO | E22: ='UNILAB - RELATÓRIO VENDAS'!E72 -> 13
B23: 19 | C23: VHS | D23: HEMOSSEDIMENTAÇÃO | E23: ='UNILAB - RELATÓRIO VENDAS'!E73 -> 8.5
B24: 20 | C24: POT | D24: K (POTASSIO) | E24: ='UNILAB - RELATÓRIO VENDAS'!E116 -> 6
B25: 21 | C25: MAG | D25: MAGNESIO | E25: ='UNILAB - RELATÓRIO VENDAS'!E103 -> 12
B26: 22 | C26: SOD | D26: NA (SODIO) | E26: ='UNILAB - RELATÓRIO VENDAS'!E136 -> 6
B27: 23 | C27: NS1 | D27: NS1 TESTE RAPIDO | E27: ='UNILAB - RELATÓRIO VENDAS'!E112 -> 68
B28: 24 | C28: PROTO | D28: PROTOPARASITOLOGICO | E28: ='UNILAB - RELATÓRIO VENDAS'!E122 -> 7.5
B29: 25 | C29: PSAT | D29: PSA | E29: ='UNILAB - RELATÓRIO VENDAS'!E14 -> 38
B30: 26 | C30: PTHI | D30: PTHI | E30: ='UNILAB - RELATÓRIO VENDAS'!E114 -> 85
B31: 27 | C31: SGOCFEZ | D31: SANGUE OCULTO NAS FEZES | E31: ='UNILAB - RELATÓRIO VENDAS'!E134 -> 12.5
B32: 28 | C32: T4 | D32: T4 TOTAL | E32: ='UNILAB - RELATÓRIO VENDAS'!E139 -> 23.8
B33: 29 | C33: T4L | D33: T4L LIVRE | E33: ='UNILAB - RELATÓRIO VENDAS'!E140 -> 24
B34: 30 | C34: TESTL | D34: TESTORONA LIVRE | E34: ='UNILAB - RELATÓRIO VENDAS'!E144 -> 39.1
B35: 31 | C35: TESTT | D35: TESTOSTERONA TOTAL | E35: ='UNILAB - RELATÓRIO VENDAS'!E145 -> 34
B36: 32 | C36: TGO | D36: TRANSAMINASE OXALACETICA | E36: ='UNILAB - RELATÓRIO VENDAS'!E149 -> 6
B37: 33 | C37: TGP | D37: TRANSAMINASE PIRUVICA | E37: ='UNILAB - RELATÓRIO VENDAS'!E150 -> 6
B38: 34 | C38: TGL | D38: TRIGLICERIDES | E38: ='UNILAB - RELATÓRIO VENDAS'!E151 -> 8.5
B39: 35 | C39: TROPO | D39: TROPOTONINA | E39: ='UNILAB - RELATÓRIO VENDAS'!E152 -> 98.6
B40: 36 | C40: TSH | D40: TSH ULTRA SENSIVEL | E40: ='UNILAB - RELATÓRIO VENDAS'!E153 -> 23
B41: 37 | C41: URE | D41: UREIA | E41: ='UNILAB - RELATÓRIO VENDAS'!E155 -> 6
B42: 38 | C42: URI2J | D42: URINA I | E42: ='UNILAB - RELATÓRIO VENDAS'!E159 -> 8.5
B43: 39 | C43: URO2JM | D43: UROCULTURA | E43: ='UNILAB - RELATÓRIO VENDAS'!E164 -> 34
B44: 40 | C44: VITB12 | D44: VIT B12 | E44: ='UNILAB - RELATÓRIO VENDAS'!E167 -> 33.405
B45: 41 | C45: 25OHVITD | D45: VIT D | E45: ='UNILAB - RELATÓRIO VENDAS'!E5 -> 34.5
B46: 42 | C46: ZN | D46: ZINCO | E46: ='UNILAB - VENDAS'!D173 -> 51.5

Sheet UNILAB - RELATÓRIO VENDAS
A1: CENTRO MÉDICO INTEGRADO 2026
A2: RELATÓRIO CUSTOS UNILAB - RELATÓRIO DE VENDAS
A3: QTDE | B3: MNEMÔNICO | C3: PROCEDIMENTO | D3: CUSTO | E3: VENDA | F3: RECEITA | G3: LUCRO
A4: SEQUÊNCIA ALFABETICA - A
A5: 1 | B5: 25OHVITD | C5: 25-HIDROXI VITAMINA D | D5: 19.5 | E5: 34.5 | F5: =E5-D5 -> 15 | G5: =E5/D5-100% -> 0.76923077
A6: 2 | B6: ACFOL | C6: ACIDO FOLICO | D6: 28 | E6: =D6*170% -> 47.6 | F6: =E6-D6 -> 19.6 | G6: =E6/D6-100% -> 0.7
A7: 3 | B7: HIPURIJ | C7: ACIDO HIPURICO, URINA - INICIO DE JORNADA | D7: 9.9 | E7: 19 | F7: =E7-D7 -> 9.1 | G7: =E7/D7-100% -> 0.91919192
A8: 4 | B8: HIPURIS | C8: ACIDO HIPURICO, URINA ISOLADA | D8: 9.9 | E8: 19 | F8: =E8-D8 -> 9.1 | G8: =E8/D8-100% -> 0.91919192
A9: 5 | B9: METHURIS | C9: ÁCIDO METIL HIPÚRICO FINAL DE JORNADA | D9: 9.9 | E9: 19 | F9: =E9-D9 -> 9.1 | G9: =E9/D9-100% -> 0.91919192
A10: 6 | B10: AMHI | C10: ÁCIDO METIL HIPÚRICO, INÍCIO DE JORNADA | D10: 9.9 | E10: 19 | F10: =E10-D10 -> 9.1 | G10: =E10/D10-100% -> 0.91919192
A11: 7 | B11: ACUR | C11: ACIDO URICO | D11: 3 | E11: 6 | F11: =E11-D11 -> 3 | G11: =E11/D11-100% -> 1
A12: 8 | B12: ALB | C12: ALBUMINA SERICA | D12: 7 | E12: =D12*170% -> 11.9 | F12: =E12-D12 -> 4.9 | G12: =E12/D12-100% -> 0.7
A13: 9 | B13: AMIL | C13: AMILASE SERICA | D13: 4 | E13: =D13*170% -> 6.8 | F13: =E13-D13 -> 2.8 | G13: =E13/D13-100% -> 0.7
A14: 10 | B14: PSAT | C14: ANTIGENO PROSTATICO ESPECIFICO | D14: 19.85 | E14: 38 | F14: =E14-D14 -> 18.15 | G14: =E14/D14-100% -> 0.91435768
A15: 11 | C15: ANTIGENO PROSTATICO ESPECIFICO TOTAL E LIVRE | D15: 19.85 | E15: 34 | F15: =E15-D15 -> 14.15 | G15: =E15/D15-100% -> 0.71284635
A16: 12 | B16: PSATL | C16: ANTIGENO PROSTATICO ESPECIFICO TOTAL E LIVRE | D16: 25 | E16: =D16*170% -> 42.5 | F16: =E16-D16 -> 17.5 | G16: =E16/D16-100% -> 0.7
A17: SEQUÊNCIA ALFABETICA - B
A18: 13 | B18: BILI# | C18: BILIRRUBINAS TOTAL E FRAÇÕES | D18: 5 | E18: =D18*170% -> 8.5 | F18: =E18-D18 -> 3.5 | G18: =E18/D18-100% -> 0.7
A19: 14 | C19: BILIRRUBINAS TOTAL E FRAÇÕES - RECÉM NASCIDOS | D19: 5 | E19: =D19*170% -> 8.5 | F19: =E19-D19 -> 3.5 | G19: =E19/D19-100% -> 0.7
A20: 15 | B20: BRUC-IGG | C20: BRUCELOSE IgG, ANTICORPOS | D20: 28 | E20: =D20*170% -> 47.6 | F20: =E20-D20 -> 19.6 | G20: =E20/D20-100% -> 0.7
A21: 16 | B21: BRUC-IGM | C21: BRUCELOSE IGM, ANTICORPOS | D21: 28 | E21: =D21*170% -> 47.6 | F21: =E21-D21 -> 19.6 | G21: =E21/D21-100% -> 0.7
A22: SEQUÊNCIA ALFABETICA - C
A23: 17 | B23: CA125 | C23: CA 125 | D23: 37 | E23: 69 | F23: =E23-D23 -> 32 | G23: =E23/D23-100% -> 0.86486486
A24: 18 | B24: CA153 | C24: CA 15-3 | D24: 50 | E24: =D24*170% -> 85 | F24: =E24-D24 -> 35 | G24: =E24/D24-100% -> 0.7
A25: 19 | B25: CA199 | C25: CA 19-9 | D25: 50 | E25: =D25*170% -> 85 | F25: =E25-D25 -> 35 | G25: =E25/D25-100% -> 0.7
A26: 20 | B26: CA724 | C26: CA 72-4 | D26: 60 | E26: =D26*170% -> 102 | F26: =E26-D26 -> 42 | G26: =E26/D26-100% -> 0.7
A27: 21 | B27: CAIONUNI | C27: CALCIO IONICO | D27: 15 | E27: =D27*170% -> 25.5 | F27: =E27-D27 -> 10.5 | G27: =E27/D27-100% -> 0.7
A28: 22 | B28: CA | C28: CALCIO SERICO | D28: 4 | E28: 7 | F28: =E28-D28 -> 3 | G28: =E28/D28-100% -> 0.75
A29: 23 | B29: TIBC | C29: CAPACIDADE TOTAL DE COMBINAÇÃO DO FERRO | D29: 6 | E29: 11 | F29: =E29-D29 -> 5 | G29: =E29/D29-100% -> 0.83333333
A30: 24 | B30: CL | C30: CLORO | D30: 4 | E30: =D30*170% -> 6.8 | F30: =E30-D30 -> 2.8 | G30: =E30/D30-100% -> 0.7
A31: 25 | B31: COAG-UNI | C31: COAGULOGRAMA | D31: 20 | E31: =D31*170% -> 34 | F31: =E31-D31 -> 14 | G31: =E31/D31-100% -> 0.7
A32: 26 | C32: COLESTEROL TOTAL | D32: 3.15 | E32: 24.5 | F32: =E32-D32 -> 21.35 | G32: =E32/D32-100% -> 6.7777778
A33: 27 | B33: COLTF | C33: COLESTEROL TOTAL E FRAÇÕES | D33: 15.3 | E33: 58 | F33: =E33-D33 -> 42.7 | G33: =E33/D33-100% -> 2.7908497
A34: 28 | B34: COPRO | C34: COPROCULTURA | D34: 13.5 | E34: 23 | F34: =E34-D34 -> 9.5 | G34: =E34/D34-100% -> 0.7037037
A35: 29 | B35: COPROE | C35: COPROCULTURA (EMPRESAS) | D35: 13.5 | E35: 23 | F35: =E35-D35 -> 9.5 | G35: =E35/D35-100% -> 0.7037037
A36: 30 | B36: CINA-S | C36: CREATINA SERICA | D36: 22 | E36: 37.4 | F36: =E36-D36 -> 15.4 | G36: =E36/D36-100% -> 0.7
A37: 31 | B37: CRE | C37: CREATININA SERICA | D37: 2.7 | E37: 6 | F37: =E37-D37 -> 3.3 | G37: =E37/D37-100% -> 1.2222222
A38: 32 | B38: CPK | C38: CREATINO FOSFOQUINASE | D38: 7.23 | E38: 12.3 | F38: =E38-D38 -> 5.07 | G38: =E38/D38-100% -> 0.70124481
A39: 33 | C39: CREATINO FOSFOQUINASE - DILUIÇÃO | D39: 7.23 | E39: =D39*170% -> 12.291 | F39: =E39-D39 -> 5.061 | G39: =E39/D39-100% -> 0.7
A40: 34 | C40: CREATINO FOSFOQUINASE POS ESFORÇO FISICO | D40: 7.23 | E40: =D40*170% -> 12.291 | F40: =E40-D40 -> 5.061 | G40: =E40/D40-100% -> 0.7
A41: 35 | B41: CR | C41: CROMO SERICO | D41: 26.4 | E41: 45 | F41: =E41-D41 -> 18.6 | G41: =E41/D41-100% -> 0.70454545
A42: SEQUÊNCIA ALFABETICA - D
A43: 36 | B43: DHEA | C43: DEHIDROEPIANDROSTERONA | D43: 25 | E43: 45 | F43: =E43-D43 -> 20 | G43: =E43/D43-100% -> 0.8
A44: 37 | B44: DENORP002 | C44: DENGUE, ANTICORPOS IgG - TESTE RÁPIDO | D44: 20 | E44: 34 | F44: =E44-D44 -> 14 | G44: =E44/D44-100% -> 0.7
A45: 38 | B45: DENORP003 | C45: DENGUE, ANTICORPOS IgM - TESTE RÁPIDO | D45: 20 | E45: 34 | F45: =E45-D45 -> 14 | G45: =E45/D45-100% -> 0.7
A46: 39 | B46: DES LA(R | C46: DESIDROGENASE LATICA | D46: 5 | E46: 10 | F46: =E46-D46 -> 5 | G46: =E46/D46-100% -> 1
A47: SEQUÊNCIA ALFABETICA - E
A48: 40 | C48: ELETROFORESE DE HEMOGLOBINA (UNILAB) | D48: 28 | E48: =D48*170% -> 47.6 | F48: =E48-D48 -> 19.6 | G48: =E48/D48-100% -> 0.7
A49: 41 | B49: ELFPROT | C49: ELETROFORESE DE PROTEINAS | D49: 26 | E49: =D49*170% -> 44.2 | F49: =E49-D49 -> 18.2 | G49: =E49/D49-100% -> 0.7
A50: 42 | B50: E2 | C50: ESTRADIOL | D50: 8 | E50: 33.5 | F50: =E50-D50 -> 25.5 | G50: =E50/D50-100% -> 3.1875
A51: 43 | B51: ESTRIOL | C51: ESTRIOL LIVRE | D51: 21.6 | E51: 38 | F51: =E51-D51 -> 16.4 | G51: =E51/D51-100% -> 0.75925926
A52: SEQUÊNCIA ALFABETICA - F
A53: 44 | B53: FAN | C53: FATOR ANTI NUCLEO | D53: 20 | E53: =D53*170% -> 34 | F53: =E53-D53 -> 14 | G53: =E53/D53-100% -> 0.7
A54: 45 | B54: FREUM | C54: FATOR REUMATOIDE (40306860) | D54: 18 | E54: =D54*170% -> 30.6 | F54: =E54-D54 -> 12.6 | G54: =E54/D54-100% -> 0.7
A55: 46 | C55: FATOR REUMATOIDE (40308030) | D55: 18 | E55: =D55*170% -> 30.6 | F55: =E55-D55 -> 12.6 | G55: =E55/D55-100% -> 0.7
A56: 47 | B56: FERR | C56: FERRITINA | D56: 35 | E56: =D56*170% -> 59.5 | F56: =E56-D56 -> 24.5 | G56: =E56/D56-100% -> 0.7
A57: 48 | B57: FE | C57: FERRO SERICO | D57: 7.23 | E57: 13 | F57: =E57-D57 -> 5.77 | G57: =E57/D57-100% -> 0.79806362
A58: 49 | B58: FOS | C58: FOSFORO SÉRICO | D58: 8 | E58: 57 | F58: =E58-D58 -> 49 | G58: =E58/D58-100% -> 6.125
A59: 50 | B59: FSH | C59: FSH - HORMONIO FOLICULO ESTIMULANTE | D59: 10.16 | E59: 28 | F59: =E59-D59 -> 17.84 | G59: =E59/D59-100% -> 1.7559055
A60: 51 | B60: FTAG | C60: FTA ABS IGG | D60: 20 | E60: =D60*170% -> 34 | F60: =E60-D60 -> 14 | G60: =E60/D60-100% -> 0.7
A61: 52 | B61: FTAM | C61: FTA-ABS IgM | D61: 20 | E61: =D61*170% -> 34 | F61: =E61-D61 -> 14 | G61: =E61/D61-100% -> 0.7
A62: 53 | B62: FUNCFEZ | C62: FUNCIONAL DE FEZES | D62: 26 | E62: 61 | F62: =E62-D62 -> 35 | G62: =E62/D62-100% -> 1.3461538
A63: SEQUÊNCIA ALFABETICA - G
A64: 54 | B64: GGT | C64: GAMA GLUTAMIL TRANSFERASE | D64: 3.15 | E64: 8.5 | F64: =E64-D64 -> 5.35 | G64: =E64/D64-100% -> 1.6984127
A65: 55 | B65: GASOV | C65: GASOMETRIA VENOSA | D65: 45 | E65: 79.5 | F65: =E65-D65 -> 34.5 | G65: =E65/D65-100% -> 0.76666667
A66: 56 | B66: GLI | C66: GLICOSE, JEJUM | D66: 2.7 | E66: 6 | F66: =E66-D66 -> 3.3 | G66: =E66/D66-100% -> 1.2222222
A67: 57 | B67: SHBG1 | C67: GLOBULINA LIGADORA DE HORMONIOS SEXUAIS | D67: 30 | E67: =D67*170% -> 51 | F67: =E67-D67 -> 21 | G67: =E67/D67-100% -> 0.7
A68: SEQUÊNCIA ALFABETICA - H
A69: 58 | B69: HDL | C69: HDL | D69: 8 | E69: 24.5 | F69: =E69-D69 -> 16.5 | G69: =E69/D69-100% -> 2.0625
A70: 59 | B70: HBA1C | C70: HEMOGLOBINA GLICADA (40302075) | D70: 13.5 | E70: 23 | F70: =E70-D70 -> 9.5 | G70: =E70/D70-100% -> 0.7037037
A71: 60 | C71: HEMOGLOBINA GLICADA (40302733) | D71: 13.5 | E71: 23 | F71: =E71-D71 -> 9.5 | G71: =E71/D71-100% -> 0.7037037
A72: 61 | B72: HEMO | C72: HEMOGRAMA COMPLETO | D72: 5.5 | E72: 13 | F72: =E72-D72 -> 7.5 | G72: =E72/D72-100% -> 1.3636364
A73: 62 | B73: VHS | C73: HEMOSSEDIMENTACAO | D73: 5 | E73: =D73*170% -> 8.5 | F73: =E73-D73 -> 3.5 | G73: =E73/D73-100% -> 0.7
A74: 63 | B74: HVA-G | C74: HEPATITE A, ANTICORPOS IgG | D74: 20 | E74: 43 | F74: =E74-D74 -> 23 | G74: =E74/D74-100% -> 1.15
A75: 64 | B75: HVA-M | C75: HEPATITE A, ANTICORPOS IgM | D75: 23 | E75: 51.5 | F75: =E75-D75 -> 28.5 | G75: =E75/D75-100% -> 1.2391304
A76: 65 | B76: ANTIHBCM | C76: HEPATITE B, ANTI HBC IGM | D76: 27 | E76: =D76*170% -> 45.9 | F76: =E76-D76 -> 18.9 | G76: =E76/D76-100% -> 0.7
A77: 66 | B77: ANTIHBCT | C77: HEPATITE B, ANTI HBC TOTAL | D77: 22 | E77: 38 | F77: =E77-D77 -> 16 | G77: =E77/D77-100% -> 0.72727273
A78: 67 | B78: ANTIHBS | C78: HEPATITE B, ANTI HBS | D78: 11.25 | E78: 27.5 | F78: =E78-D78 -> 16.25 | G78: =E78/D78-100% -> 1.4444444
A79: 68 | B79: AHBE | C79: HEPATITE B, ANTICORPOS ANTIGENO E | D79: 30 | E79: =D79*170% -> 51 | F79: =E79-D79 -> 21 | G79: =E79/D79-100% -> 0.7
A80: 69 | B80: HBE | C80: HEPATITE B, ANTIGENO E | D80: 34 | E80: =D80*170% -> 57.8 | F80: =E80-D80 -> 23.8 | G80: =E80/D80-100% -> 0.7
A81: 70 | B81: HBSAG | C81: HEPATITE B, HBsAg (40307018) | D81: 11.25 | E81: 26 | F81: =E81-D81 -> 14.75 | G81: =E81/D81-100% -> 1.3111111
A82: 71 | C82: HEPATITE B, HBsAg (40316114) | D82: 11.25 | E82: 26 | F82: =E82-D82 -> 14.75 | G82: =E82/D82-100% -> 1.3111111
A83: 72 | B83: HCV | C83: HEPATITE C, ANTICORPOS (ANTI HCV) (40307026) | D83: 21.9 | E83: 54.5 | F83: =E83-D83 -> 32.6 | G83: =E83/D83-100% -> 1.4885845
A84: 73 | C84: HEPATITE C, ANTICORPOS (ANTI HCV) (40307034) | D84: 21.9 | E84: 54.5 | F84: =E84-D84 -> 32.6 | G84: =E84/D84-100% -> 1.4885845
A85: 74 | B85: HIV | C85: HIV, ANTICORPOS (40307174) | D85: 28 | E85: 69 | F85: =E85-D85 -> 41 | G85: =E85/D85-100% -> 1.4642857
A86: 75 | C86: HIV, ANTICORPOS (40307182) | D86: 28 | E86: 69 | F86: =E86-D86 -> 41 | G86: =E86/D86-100% -> 1.4642857
A87: 76 | B87: HOM | C87: HOMOCISTEINA | D87: 60 | E87: =D87*170% -> 102 | F87: =E87-D87 -> 42 | G87: =E87/D87-100% -> 0.7
A88: SEQUÊNCIA ALFABETICA - I
A89: 77 | C89: IGE ESPECÍFICA PARA DEXAMETASONA (C350) | D89: 30 | E89: =D89*170% -> 51 | F89: =E89-D89 -> 21 | G89: =E89/D89-100% -> 0.7
A90: 78 | C90: IGE PARA FORMIGA LAVA-PE (I70) | D90: 25 | E90: =D90*170% -> 42.5 | F90: =E90-D90 -> 17.5 | G90: =E90/D90-100% -> 0.7
A91: 79 | C91: IGE PARA MARIMBONDO (I4) | D91: 33 | E91: =D91*170% -> 56.1 | F91: =E91-D91 -> 23.1 | G91: =E91/D91-100% -> 0.7
A92: 80 | C92: IGE PARA VENENO DE ABELHA (I1) | D92: 25 | E92: =D92*170% -> 42.5 | F92: =E92-D92 -> 17.5 | G92: =E92/D92-100% -> 0.7
A93: 81 | C93: IGE PARA VENENO DE VESPA (I3) | D93: 33 | E93: =D93*170% -> 56.1 | F93: =E93-D93 -> 23.1 | G93: =E93/D93-100% -> 0.7
A94: 82 | C94: IMUNOGLOBULINA A (IgA) | D94: 15 | E94: =D94*170% -> 25.5 | F94: =E94-D94 -> 10.5 | G94: =E94/D94-100% -> 0.7
A95: 83 | C95: IMUNOGLOBULINA G (IgG) | D95: 15 | E95: =D95*170% -> 25.5 | F95: =E95-D95 -> 10.5 | G95: =E95/D95-100% -> 0.7
A96: 84 | C96: IMUNOGLOBULINA M (IgM) | D96: 15 | E96: =D96*170% -> 25.5 | F96: =E96-D96 -> 10.5 | G96: =E96/D96-100% -> 0.7
A97: SEQUÊNCIA ALFABETICA - L
A98: 85 | C98: LACTOSE, TESTE DE ABSORÇÃO | D98: 15 | E98: 34 | F98: =E98-D98 -> 19 | G98: =E98/D98-100% -> 1.2666667
A99: 86 | B99: LACT-3T | C99: LACTOSE, TESTE DE ABSORÇÃO 0,30, 60 MIN | D99: 15 | E99: 34 | F99: =E99-D99 -> 19 | G99: =E99/D99-100% -> 1.2666667
A100: 87 | B100: LH | C100: LH - HORMONIO LUTEINIZANTE | D100: 10.16 | E100: 27 | F100: =E100-D100 -> 16.84 | G100: =E100/D100-100% -> 1.6574803
...

Sheet UNILAB - VENDAS
A1: CENTRO MÉDICO INTEGRADO 2026
A2: UNILAB - EXAMES LABORATORIAIS
A3: QTDE | B3: MNEMÔNICO | C3: PROCEDIMENTO | D3: VENDA
A4: SEQUÊNCIA ALFABÉTICA - A
A5: 1 | B5: ACFOL | C5: ACIDO FOLICO | D5: ='UNILAB - RELATÓRIO VENDAS'!E6 -> 47.6
A6: 2 | B6: HIPURIJ | C6: ACIDO HIPURICO, URINA - INICIO DE JORNADA | D6: ='UNILAB - RELATÓRIO VENDAS'!E7 -> 19
A7: 3 | B7: HIPURIS | C7: ACIDO HIPURICO, URINA ISOLADA | D7: ='UNILAB - RELATÓRIO VENDAS'!E8 -> 19
A8: 4 | B8: METHURIS | C8: ÁCIDO METIL HIPÚRICO FINAL DE JORNADA | D8: ='UNILAB - RELATÓRIO VENDAS'!E9 -> 19
A9: 5 | B9: AMHI | C9: ÁCIDO METIL HIPÚRICO, INÍCIO DE JORNADA | D9: ='UNILAB - RELATÓRIO VENDAS'!E10 -> 19
A10: 6 | B10: ACUR | C10: ACIDO URICO | D10: ='UNILAB - RELATÓRIO VENDAS'!E11 -> 6
A11: 7 | B11: ALB | C11: ALBUMINA SERICA | D11: ='UNILAB - RELATÓRIO VENDAS'!E12 -> 11.9
A12: 8 | B12: AMIL | C12: AMILASE SERICA | D12: ='UNILAB - RELATÓRIO VENDAS'!E13 -> 6.8
A13: 9 | B13: PSAT | C13: ANTIGENO PROSTATICO ESPECIFICO | D13: ='UNILAB - RELATÓRIO VENDAS'!E14 -> 38
A14: 10 | C14: ANTIGENO PROSTATICO ESPECIFICO TOTAL E LIVRE | D14: ='UNILAB - RELATÓRIO VENDAS'!E15 -> 34
A15: 11 | B15: PSATL | C15: ANTIGENO PROSTATICO ESPECIFICO TOTAL E LIVRE | D15: ='UNILAB - RELATÓRIO VENDAS'!E16 -> 42.5
A16: SEQUÊNCIA ALFABÉTICA - B
A17: 12 | B17: BILI# | C17: BILIRRUBINAS TOTAL E FRAÇÕES | D17: ='UNILAB - RELATÓRIO VENDAS'!E18 -> 8.5
A18: 13 | C18: BILIRRUBINAS TOTAL E FRAÇÕES - RECÉM NASCIDOS | D18: ='UNILAB - RELATÓRIO VENDAS'!E19 -> 8.5
A19: 14 | B19: BRUC-IGG | C19: BRUCELOSE IgG, ANTICORPOS | D19: ='UNILAB - RELATÓRIO VENDAS'!E20 -> 47.6
A20: 15 | B20: BRUC-IGM | C20: BRUCELOSE IGM, ANTICORPOS | D20: ='UNILAB - RELATÓRIO VENDAS'!E21 -> 47.6
A21: SEQUÊNCIA ALFABÉTICA - C
A22: 16 | B22: CA125 | C22: CA 125 | D22: ='UNILAB - RELATÓRIO VENDAS'!E23 -> 69
A23: 17 | B23: CA153 | C23: CA 15-3 | D23: ='UNILAB - RELATÓRIO VENDAS'!E24 -> 85
A24: 18 | B24: CA199 | C24: CA 19-9 | D24: ='UNILAB - RELATÓRIO VENDAS'!E25 -> 85
A25: 19 | B25: CA724 | C25: CA 72-4 | D25: ='UNILAB - RELATÓRIO VENDAS'!E26 -> 102
A26: 20 | B26: CAIONUNI | C26: CALCIO IONICO | D26: ='UNILAB - RELATÓRIO VENDAS'!E27 -> 25.5
A27: 21 | B27: CA | C27: CALCIO SERICO | D27: ='UNILAB - RELATÓRIO VENDAS'!E28 -> 7
A28: 22 | B28: TIBC | C28: CAPACIDADE TOTAL DE COMBINAÇÃO DO FERRO | D28: ='UNILAB - RELATÓRIO VENDAS'!E29 -> 11
A29: 23 | B29: CL | C29: CLORO | D29: ='UNILAB - RELATÓRIO VENDAS'!E30 -> 6.8
A30: 24 | B30: COAG-UNI | C30: COAGULOGRAMA | D30: ='UNILAB - RELATÓRIO VENDAS'!E31 -> 34
A31: 25 | C31: COLESTEROL TOTAL | D31: ='UNILAB - RELATÓRIO VENDAS'!E32 -> 24.5
A32: 26 | B32: COLTF | C32: COLESTEROL TOTAL E FRAÇÕES | D32: ='UNILAB - RELATÓRIO VENDAS'!E33 -> 58
A33: 27 | B33: COPRO | C33: COPROCULTURA | D33: ='UNILAB - RELATÓRIO VENDAS'!E34 -> 23
A34: 28 | B34: COPROE | C34: COPROCULTURA (EMPRESAS) | D34: ='UNILAB - RELATÓRIO VENDAS'!E35 -> 23
A35: 29 | B35: CINA-S | C35: CREATINA SERICA | D35: ='UNILAB - RELATÓRIO VENDAS'!E36 -> 37.4
A36: 30 | B36: CRE | C36: CREATININA SERICA | D36: ='UNILAB - RELATÓRIO VENDAS'!E37 -> 6
A37: 31 | B37: CPK | C37: CREATINO FOSFOQUINASE | D37: ='UNILAB - RELATÓRIO VENDAS'!E38 -> 12.3
A38: 32 | C38: CREATINO FOSFOQUINASE - DILUIÇÃO | D38: ='UNILAB - RELATÓRIO VENDAS'!E39 -> 12.291
A39: 33 | C39: CREATINO FOSFOQUINASE POS ESFORÇO FISICO | D39: ='UNILAB - RELATÓRIO VENDAS'!E40 -> 12.291
A40: 34 | B40: CR | C40: CROMO SERICO | D40: ='UNILAB - RELATÓRIO VENDAS'!E41 -> 45
A41: SEQUÊNCIA ALFABÉTICA - D
A42: 35 | B42: DHEA | C42: DEHIDROEPIANDROSTERONA | D42: ='UNILAB - RELATÓRIO VENDAS'!E43 -> 45
A43: 36 | B43: DENORP002 | C43: DENGUE, ANTICORPOS IgG - TESTE RÁPIDO | D43: ='UNILAB - RELATÓRIO VENDAS'!E44 -> 34
A44: 37 | B44: DENORP003 | C44: DENGUE, ANTICORPOS IgM - TESTE RÁPIDO | D44: ='UNILAB - RELATÓRIO VENDAS'!E45 -> 34
A45: 38 | B45: DES LA(R | C45: DESIDROGENASE LATICA | D45: ='UNILAB - RELATÓRIO VENDAS'!E46 -> 10
A46: SEQUÊNCIA ALFABÉTICA - E
A47: 39 | C47: ELETROFORESE DE HEMOGLOBINA (UNILAB) | D47: ='UNILAB - RELATÓRIO VENDAS'!E48 -> 47.6
A48: 40 | B48: ELFPROT | C48: ELETROFORESE DE PROTEINAS | D48: ='UNILAB - RELATÓRIO VENDAS'!E49 -> 44.2
A49: 41 | B49: E2 | C49: ESTRADIOL | D49: ='UNILAB - RELATÓRIO VENDAS'!E50 -> 33.5
A50: 42 | B50: ESTRIOL | C50: ESTRIOL LIVRE | D50: ='UNILAB - RELATÓRIO VENDAS'!E51 -> 38
A51: SEQUÊNCIA ALFABÉTICA - F
A52: 43 | B52: FAN | C52: FATOR ANTI NUCLEO | D52: ='UNILAB - RELATÓRIO VENDAS'!E53 -> 34
A53: 44 | B53: FREUM | C53: FATOR REUMATOIDE (40306860) | D53: ='UNILAB - RELATÓRIO VENDAS'!E54 -> 30.6
A54: 45 | C54: FATOR REUMATOIDE (40308030) | D54: ='UNILAB - RELATÓRIO VENDAS'!E55 -> 30.6
A55: 46 | B55: FERR | C55: FERRITINA | D55: ='UNILAB - RELATÓRIO VENDAS'!E56 -> 59.5
A56: 47 | B56: FE | C56: FERRO SERICO | D56: ='UNILAB - RELATÓRIO VENDAS'!E57 -> 13
A57: 48 | B57: FOS | C57: FOSFORO SÉRICO | D57: ='UNILAB - RELATÓRIO VENDAS'!E58 -> 57
A58: 49 | B58: FSH | C58: FSH - HORMONIO FOLICULO ESTIMULANTE | D58: ='UNILAB - RELATÓRIO VENDAS'!E59 -> 28
A59: 50 | B59: FTAG | C59: FTA ABS IGG | D59: ='UNILAB - RELATÓRIO VENDAS'!E60 -> 34
A60: 51 | B60: FTAM | C60: FTA-ABS IgM | D60: ='UNILAB - RELATÓRIO VENDAS'!E61 -> 34
A61: 52 | B61: FUNCFEZ | C61: FUNCIONAL DE FEZES | D61: ='UNILAB - RELATÓRIO VENDAS'!E62 -> 61
A62: SEQUÊNCIA ALFABÉTICA - G
A63: 53 | B63: GGT | C63: GAMA GLUTAMIL TRANSFERASE | D63: ='UNILAB - RELATÓRIO VENDAS'!E64 -> 8.5
A64: 54 | B64: GASOV | C64: GASOMETRIA VENOSA | D64: ='UNILAB - RELATÓRIO VENDAS'!E65 -> 79.5
A65: 55 | B65: GLI | C65: GLICOSE, JEJUM | D65: ='UNILAB - RELATÓRIO VENDAS'!E66 -> 6
A66: 56 | B66: SHBG1 | C66: GLOBULINA LIGADORA DE HORMONIOS SEXUAIS | D66: ='UNILAB - RELATÓRIO VENDAS'!E67 -> 51
A67: SEQUÊNCIA ALFABÉTICA - H
A68: 57 | B68: HDL | C68: HDL | D68: ='UNILAB - RELATÓRIO VENDAS'!E69 -> 24.5
A69: 58 | B69: 25OHVITD | C69: 25-HIDROXI VITAMINA D | D69: ='UNILAB - RELATÓRIO VENDAS'!E70 -> 23
A70: 59 | B70: HBA1C | C70: HEMOGLOBINA GLICADA (40302075) | D70: ='UNILAB - RELATÓRIO VENDAS'!E70 -> 23
A71: 60 | C71: HEMOGLOBINA GLICADA (40302733) | D71: ='UNILAB - RELATÓRIO VENDAS'!E71 -> 23
A72: 61 | B72: HEMO | C72: HEMOGRAMA COMPLETO | D72: ='UNILAB - RELATÓRIO VENDAS'!E72 -> 13
A73: 62 | B73: VHS | C73: HEMOSSEDIMENTACAO | D73: ='UNILAB - RELATÓRIO VENDAS'!E73 -> 8.5
A74: 63 | B74: HVA-G | C74: HEPATITE A, ANTICORPOS IgG | D74: ='UNILAB - RELATÓRIO VENDAS'!E74 -> 43
A75: 64 | B75: HVA-M | C75: HEPATITE A, ANTICORPOS IgM | D75: ='UNILAB - RELATÓRIO VENDAS'!E75 -> 51.5
A76: 65 | B76: ANTIHBCM | C76: HEPATITE B, ANTI HBC IGM | D76: ='UNILAB - RELATÓRIO VENDAS'!E76 -> 45.9
A77: 66 | B77: ANTIHBCT | C77: HEPATITE B, ANTI HBC TOTAL | D77: ='UNILAB - RELATÓRIO VENDAS'!E77 -> 38
A78: 67 | B78: ANTIHBS | C78: HEPATITE B, ANTI HBS | D78: ='UNILAB - RELATÓRIO VENDAS'!E78 -> 27.5
A79: 68 | B79: AHBE | C79: HEPATITE B, ANTICORPOS ANTIGENO E | D79: ='UNILAB - RELATÓRIO VENDAS'!E79 -> 51
A80: 69 | B80: HBE | C80: HEPATITE B, ANTIGENO E | D80: ='UNILAB - RELATÓRIO VENDAS'!E80 -> 57.8
A81: 70 | B81: HBSAG | C81: HEPATITE B, HBsAg (40307018) | D81: ='UNILAB - RELATÓRIO VENDAS'!E81 -> 26
A82: 71 | C82: HEPATITE B, HBsAg (40316114) | D82: ='UNILAB - RELATÓRIO VENDAS'!E82 -> 26
A83: 72 | B83: HCV | C83: HEPATITE C, ANTICORPOS (ANTI HCV) (40307026) | D83: ='UNILAB - RELATÓRIO VENDAS'!E83 -> 54.5
A84: 73 | C84: HEPATITE C, ANTICORPOS (ANTI HCV) (40307034) | D84: ='UNILAB - RELATÓRIO VENDAS'!E84 -> 54.5
A85: 74 | B85: HIV | C85: HIV, ANTICORPOS (40307174) | D85: ='UNILAB - RELATÓRIO VENDAS'!E85 -> 69
A86: 75 | C86: HIV, ANTICORPOS (40307182) | D86: ='UNILAB - RELATÓRIO VENDAS'!E86 -> 69
A87: 76 | B87: HOM | C87: HOMOCISTEINA | D87: ='UNILAB - RELATÓRIO VENDAS'!E87 -> 102
A88: SEQUÊNCIA ALFABÉTICA - I
A89: 77 | C89: IGE ESPECÍFICA PARA DEXAMETASONA (C350) | D89: ='UNILAB - RELATÓRIO VENDAS'!E89 -> 51
A90: 78 | C90: IGE PARA FORMIGA LAVA-PE (I70) | D90: ='UNILAB - RELATÓRIO VENDAS'!E90 -> 42.5
A91: 79 | C91: IGE PARA MARIMBONDO (I4) | D91: ='UNILAB - RELATÓRIO VENDAS'!E91 -> 56.1
A92: 80 | C92: IGE PARA VENENO DE ABELHA (I1) | D92: ='UNILAB - RELATÓRIO VENDAS'!E92 -> 42.5
A93: 81 | C93: IGE PARA VENENO DE VESPA (I3) | D93: ='UNILAB - RELATÓRIO VENDAS'!E93 -> 56.1
A94: 82 | C94: IMUNOGLOBULINA A (IgA) | D94: ='UNILAB - RELATÓRIO VENDAS'!E94 -> 25.5
A95: 83 | C95: IMUNOGLOBULINA G (IgG) | D95: ='UNILAB - RELATÓRIO VENDAS'!E95 -> 25.5
A96: 84 | C96: IMUNOGLOBULINA M (IgM) | D96: ='UNILAB - RELATÓRIO VENDAS'!E96 -> 25.5
A97: SEQUÊNCIA ALFABÉTICA - L
A98: 85 | C98: LACTOSE, TESTE DE ABSORÇÃO | D98: ='UNILAB - RELATÓRIO VENDAS'!E98 -> 34
A99: 86 | B99: LACT-3T | C99: LACTOSE, TESTE DE ABSORÇÃO 0,30, 60 MIN | D99: ='UNILAB - RELATÓRIO VENDAS'!E99 -> 34
A100: 87 | B100: LH | C100: LH - HORMONIO LUTEINIZANTE | D100: ='UNILAB - RELATÓRIO VENDAS'!E100 -> 27
...
